Cheb3D/PyNumSpec.cpp
Cheb3D/PyNumSpec.cpython-312-darwin.so
Cheb3D/PyNumSpec.pxd
Cheb3D/PyNumSpec.pyx
Cheb3D/__init__.py
Cheb3D/funccoefs.cpp
Cheb3D/funcder.cpp
Cheb3D/funcmath.cpp
Cheb3D/funcspec.cpp
Cheb3D/funcspec.hpp
Cheb3D/funcspec_interp.cpp
Cheb3D/ppl.cpp
Cheb3D/tabmath.cpp
Cheb3D/tabspec.cpp
Cheb3D/tabspec.hpp
Cheb3D-0.3.0.dist-info/LICENSE.md
Cheb3D-0.3.0.dist-info/METADATA
Cheb3D-0.3.0.dist-info/WHEEL
Cheb3D-0.3.0.dist-info/top_level.txt
Cheb3D-0.3.0.dist-info/RECORD
