Metadata-Version: 2.1
Name: Cheb3D
Version: 0.3.0
Summary: fitting function with Chebichev polynomial on spectral grid
Author: Marco Mancini
Author-email: Marco Mancini <marco.mancini@obspm.fr>, Jerome Novak <jerome.novak@astro.unistra.fr>, Eric Gourgoulhon <eric.gourgoulhon@obspm.fr>
Maintainer-email: Marco Mancini <marco.mancini@obspm.fr>
Classifier: Programming Language :: Python :: 3
Classifier: Programming Language :: Python :: 3.6
Classifier: Programming Language :: Python :: 3.8
Classifier: Programming Language :: Python :: 3.9
Classifier: License :: OSI Approved :: GNU General Public License v3 or later (GPLv3+)
Classifier: Operating System :: OS Independent
Requires-Python: >=3.7
License-File: LICENSE.md
